nx_arxivgen/__init__.py
nx_arxivgen/generators/mckay_wormald.py
networkx_arxiv_generators-0.1.1.dist-info/METADATA
networkx_arxiv_generators-0.1.1.dist-info/WHEEL
networkx_arxiv_generators-0.1.1.dist-info/licenses/LICENSE
networkx_arxiv_generators-0.1.1.dist-info/RECORD
