Metadata-Version: 2.4
Name: networkx-arxiv-generators
Version: 0.1.1
Summary: Advanced NetworkX graph generation models implementing algorithms from mathematical papers.
Project-URL: Homepage, https://github.com/YanYablonovskiy/networkx-arxiv-generators
Project-URL: Issues, https://github.com/YanYablonovskiy/networkx-arxiv-generators/issues
Project-URL: Source, https://github.com/YanYablonovskiy/networkx-arxiv-generators
Author-email: Yan <yablonovskiy.yan@gmail.com>
License: BSD-3-Clause
License-File: LICENSE
Keywords: arxiv,generators,graphs,models,networks,networkx,random graphs
Classifier: Development Status :: 3 - Alpha
Classifier: Intended Audience :: Science/Research
Classifier: License :: OSI Approved :: BSD License
Classifier: Programming Language :: Python :: 3
Classifier: Programming Language :: Python :: 3.10
Classifier: Programming Language :: Python :: 3.11
Classifier: Programming Language :: Python :: 3.12
Classifier: Programming Language :: Python :: 3.13
Classifier: Topic :: Scientific/Engineering :: Mathematics
Requires-Python: >=3.10
Requires-Dist: networkx>=3.2
Provides-Extra: docs
Requires-Dist: mkdocs-material>=9.5; extra == 'docs'
Requires-Dist: mkdocs>=1.5; extra == 'docs'
Requires-Dist: mkdocstrings[python]>=0.24; extra == 'docs'
Provides-Extra: lint
Requires-Dist: black>=24.0.0; extra == 'lint'
Requires-Dist: mypy>=1.8.0; extra == 'lint'
Requires-Dist: ruff>=0.4.0; extra == 'lint'
Requires-Dist: types-setuptools; extra == 'lint'
Provides-Extra: test
Requires-Dist: pytest-cov>=4.0; extra == 'test'
Requires-Dist: pytest>=7.0; extra == 'test'
